telemetry_1a23/__init__.py
telemetry_1a23/__version__.py
1a23_telemetry-1.0.0.dist-info/LICENSE.rst
1a23_telemetry-1.0.0.dist-info/METADATA
1a23_telemetry-1.0.0.dist-info/WHEEL
1a23_telemetry-1.0.0.dist-info/top_level.txt
1a23_telemetry-1.0.0.dist-info/RECORD
